[
    {"code": "ATL", "name": "Hartsfield-Jackson Atlanta International Airport"},
    {"code": "LAX", "name": "Los Angeles International Airport"},
    {"code": "ORD", "name": "O'Hare International Airport"},
    {"code": "DFW", "name": "Dallas/Fort Worth International Airport"},
    {"code": "DEN", "name": "Denver International Airport"},
    {"code": "JFK", "name": "John F. Kennedy International Airport"},
    {"code": "SFO", "name": "San Francisco International Airport"},
    {"code": "LAS", "name": "McCarran International Airport"},
    {"code": "SEA", "name": "Seattle-Tacoma International Airport"},
    {"code": "MCO", "name": "Orlando International Airport"},
    {"code": "EWR", "name": "Newark Liberty International Airport"},
    {"code": "MIA", "name": "Miami International Airport"},
    {"code": "CLT", "name": "Charlotte Douglas International Airport"},
    {"code": "PHX", "name": "Phoenix Sky Harbor International Airport"},
    {"code": "IAH", "name": "George Bush Intercontinental Airport"},
    {"code": "LGA", "name": "LaGuardia Airport"},
    {"code": "LHR", "name": "London Heathrow Airport"},
    {"code": "LGW", "name": "London Gatwick Airport"},
    {"code": "CDG", "name": "Paris Charles de Gaulle Airport"},
    {"code": "AMS", "name": "Amsterdam Airport Schiphol"},
    {"code": "FRA", "name": "Frankfurt Airport"},
    {"code": "DXB", "name": "Dubai International Airport"},
    {"code": "HKG", "name": "Hong Kong International Airport"},
    {"code": "SIN", "name": "Singapore Changi Airport"},
    {"code": "ICN", "name": "Incheon International Airport"},
    {"code": "PEK", "name": "Beijing Capital International Airport"},
    {"code": "HND", "name": "Haneda Airport"},
    {"code": "SYD", "name": "Sydney Airport"},
    {"code": "CAN", "name": "Guangzhou Baiyun International Airport"},
    {"code": "BKK", "name": "Suvarnabhumi Airport"},
    {"code": "KUL", "name": "Kuala Lumpur International Airport"},
    {"code": "CGK", "name": "Soekarno-Hatta International Airport"},
    {"code": "DEL", "name": "Indira Gandhi International Airport"},
    {"code": "BOM", "name": "Chhatrapati Shivaji Maharaj International Airport"},
    {"code": "DXB", "name": "Dubai International Airport"},
    {"code": "FCO", "name": "Leonardo da Vinci–Fiumicino Airport"},
    {"code": "MAD", "name": "Adolfo Suárez Madrid–Barajas Airport"},
    {"code": "BCN", "name": "Barcelona–El Prat Airport"},
    {"code": "IST", "name": "Istanbul Airport"},
    {"code": "DME", "name": "Domodedovo International Airport"},
    {"code": "SVO", "name": "Sheremetyevo International Airport"},
    {"code": "LED", "name": "Pulkovo Airport"},
    {"code": "JFK", "name": "John F. Kennedy International Airport"},
    {"code": "LGA", "name": "LaGuardia Airport"},
    {"code": "EWR", "name": "Newark Liberty International Airport"},
    {"code": "PHL", "name": "Philadelphia International Airport"},
    {"code": "BOS", "name": "Logan International Airport"},
    {"code": "DCA", "name": "Ronald Reagan Washington National Airport"},
    {"code": "ORD", "name": "O'Hare International Airport"},
    {"code": "MDW", "name": "Chicago Midway International Airport"},
    {"code": "SFO", "name": "San Francisco International Airport"},
    {"code": "SJC", "name": "Norman Y. Mineta San José International Airport"},
    {"code": "OAK", "name": "Oakland International Airport"},
    {"code": "LAX", "name": "Los Angeles International Airport"},
    {"code": "ONT", "name": "Ontario International Airport"},
    {"code": "SAN", "name": "San Diego International Airport"},
    {"code": "SEA", "name": "Seattle-Tacoma International Airport"},
    {"code": "PHX", "name": "Phoenix Sky Harbor International Airport"},
    {"code": "PDX", "name": "Portland International Airport"},
    {"code": "LAS", "name": "McCarran International Airport"},
    {"code": "SLC", "name": "Salt Lake City International Airport"},
    {"code": "DEN", "name": "Denver International Airport"},
    {"code": "DFW", "name": "Dallas/Fort Worth International Airport"},
    {"code": "IAH", "name": "George Bush Intercontinental Airport"},
    {"code": "ATL", "name": "Hartsfield-Jackson Atlanta International Airport"},
    {"code": "MCO", "name": "Orlando International Airport"},
    {"code": "MIA", "name": "Miami International Airport"},
    {"code": "TPA", "name": "Tampa International Airport"},
    {"code": "FLL", "name": "Fort Lauderdale-Hollywood International Airport"},
    {"code": "RSW", "name": "Southwest Florida International Airport"},
    {"code": "JAX", "name": "Jacksonville International Airport"},
    {"code": "MSP", "name": "Minneapolis-Saint Paul International Airport"},
    {"code": "DTW", "name": "Detroit Metropolitan Airport"},
    {"code": "BNA", "name": "Nashville International Airport"},
    {"code": "STL", "name": "St. Louis Lambert International Airport"},
    {"code": "MDW", "name": "Chicago Midway International Airport"},
    {"code": "ORD", "name": "O'Hare International Airport"},
    {"code": "IND", "name": "Indianapolis International Airport"},
    {"code": "MCI", "name": "Kansas City International Airport"},
    {"code": "DAL", "name": "Dallas Love Field"},
    {"code": "DFW", "name": "Dallas/Fort Worth International Airport"},
    {"code": "HOU", "name": "William P. Hobby Airport"},
    {"code": "AUS", "name": "Austin-Bergstrom International Airport"},
    {"code": "IAH", "name": "George Bush Intercontinental Airport"},
    {"code": "SAT", "name": "San Antonio International Airport"},
    {"code": "MSY", "name": "Louis Armstrong New Orleans International Airport"},
    {"code": "HNL", "name": "Daniel K. Inouye International Airport"},
    {"code": "OGG", "name": "Kahului Airport"},
    {"code": "KOA", "name": "Kona International Airport"},
    {"code": "LIH", "name": "Lihue Airport"},
    {"code": "ANC", "name": "Ted Stevens Anchorage International Airport"},
    {"code": "ITO", "name": "Hilo International Airport"},
    {"code": "BOI", "name": "Boise Airport"},
    {"code": "GEG", "name": "Spokane International Airport"},
    {"code": "PSC", "name": "Tri-Cities Airport"},
    {"code": "SEA", "name": "Seattle-Tacoma International Airport"},
    {"code": "YKM", "name": "Yakima Air Terminal"},
    {"code": "PDX", "name": "Portland International Airport"},
    {"code": "SFO", "name": "San Francisco International Airport"},
    {"code": "OAK", "name": "Oakland International Airport"},
    {"code": "SJC", "name": "Norman Y. Mineta San José International Airport"},
    {"code": "SMF", "name": "Sacramento International Airport"},
    {"code": "RNO", "name": "Reno-Tahoe International Airport"},
    {"code": "BUR", "name": "Hollywood Burbank Airport"},
    {"code": "LAX", "name": "Los Angeles International Airport"},
    {"code": "ONT", "name": "Ontario International Airport"},
    {"code": "SAN", "name": "San Diego International Airport"},
    {"code": "SNA", "name": "John Wayne Airport"},
    {"code": "LAS", "name": "McCarran International Airport"},
    {"code": "PHX", "name": "Phoenix Sky Harbor International Airport"},
    {"code": "TUS", "name": "Tucson International Airport"},
    {"code": "ABQ", "name": "Albuquerque International Sunport"},
    {"code": "DEN", "name": "Denver International Airport"},
    {"code": "GEG", "name": "Spokane International Airport"},
    {"code": "PSC", "name": "Tri-Cities Airport"},
    {"code": "SEA", "name": "Seattle-Tacoma International Airport"}
  ]
  